requests_base/__init__.py
requests_base/requests_base.py
requests_base-0.1.1.dist-info/LICENSE.md
requests_base-0.1.1.dist-info/WHEEL
requests_base-0.1.1.dist-info/METADATA
requests_base-0.1.1.dist-info/RECORD
