Metadata-Version: 2.1
Name: requests-base
Version: 0.1.1
Summary: 
Home-page: https://github.com/michaeltinsley/requests-base/
License: MIT
Keywords: Requests,API
Author: Michael Tinsley
Author-email: michaeltinsley@outlook.com
Maintainer: Michael Tinsley
Maintainer-email: michaeltinsley@outlook.com
Requires-Python: >=3.6.2,<4.0.0
Classifier: License :: OSI Approved :: MIT License
Classifier: Programming Language :: Python :: 3
Classifier: Programming Language :: Python :: 3.7
Classifier: Programming Language :: Python :: 3.8
Classifier: Programming Language :: Python :: 3.9
Requires-Dist: requests (>=2.26.0,<3.0.0)
Project-URL: Repository, https://github.com/michaeltinsley/requests-base/
